oslili/__init__.py
oslili/identifier.py
oslili/datasets/cr_neg
oslili/datasets/cr_pos
oslili/spdx/0BSD.txt
oslili/spdx/389-exception.txt
oslili/spdx/AAL.txt
oslili/spdx/ADSL.txt
oslili/spdx/AFL-1.1.txt
oslili/spdx/AFL-1.2.txt
oslili/spdx/AFL-2.0.txt
oslili/spdx/AFL-2.1.txt
oslili/spdx/AFL-3.0.txt
oslili/spdx/AGPL-1.0-only.txt
oslili/spdx/AGPL-1.0-or-later.txt
oslili/spdx/AGPL-3.0-only.txt
oslili/spdx/AGPL-3.0-or-later.txt
oslili/spdx/AMDPLPA.txt
oslili/spdx/AML.txt
oslili/spdx/AMPAS.txt
oslili/spdx/ANTLR-PD-fallback.txt
oslili/spdx/ANTLR-PD.txt
oslili/spdx/APAFML.txt
oslili/spdx/APL-1.0.txt
oslili/spdx/APSL-1.0.txt
oslili/spdx/APSL-1.1.txt
oslili/spdx/APSL-1.2.txt
oslili/spdx/APSL-2.0.txt
oslili/spdx/Abstyles.txt
oslili/spdx/AdaCore-doc.txt
oslili/spdx/Adobe-2006.txt
oslili/spdx/Adobe-Glyph.txt
oslili/spdx/Afmparse.txt
oslili/spdx/Aladdin.txt
oslili/spdx/Apache-1.0.txt
oslili/spdx/Apache-1.1.txt
oslili/spdx/Apache-2.0.txt
oslili/spdx/App-s2p.txt
oslili/spdx/Arphic-1999.txt
oslili/spdx/Artistic-1.0-Perl.txt
oslili/spdx/Artistic-1.0-cl8.txt
oslili/spdx/Artistic-1.0.txt
oslili/spdx/Artistic-2.0.txt
oslili/spdx/Autoconf-exception-2.0.txt
oslili/spdx/Autoconf-exception-3.0.txt
oslili/spdx/Autoconf-exception-generic.txt
oslili/spdx/Autoconf-exception-macro.txt
oslili/spdx/BSD-1-Clause.txt
oslili/spdx/BSD-2-Clause-Patent.txt
oslili/spdx/BSD-2-Clause-Views.txt
oslili/spdx/BSD-2-Clause.txt
oslili/spdx/BSD-3-Clause-Attribution.txt
oslili/spdx/BSD-3-Clause-Clear.txt
oslili/spdx/BSD-3-Clause-LBNL.txt
oslili/spdx/BSD-3-Clause-Modification.txt
oslili/spdx/BSD-3-Clause-No-Military-License.txt
oslili/spdx/BSD-3-Clause-No-Nuclear-License-2014.txt
oslili/spdx/BSD-3-Clause-No-Nuclear-License.txt
oslili/spdx/BSD-3-Clause-No-Nuclear-Warranty.txt
oslili/spdx/BSD-3-Clause-Open-MPI.txt
oslili/spdx/BSD-3-Clause.txt
oslili/spdx/BSD-4-Clause-Shortened.txt
oslili/spdx/BSD-4-Clause-UC.txt
oslili/spdx/BSD-4-Clause.txt
oslili/spdx/BSD-4.3RENO.txt
oslili/spdx/BSD-4.3TAHOE.txt
oslili-0.15.dist-info/LICENSE
oslili-0.15.dist-info/METADATA
oslili-0.15.dist-info/NOTICE
oslili-0.15.dist-info/WHEEL
oslili-0.15.dist-info/top_level.txt
oslili-0.15.dist-info/RECORD
