Metadata-Version: 2.1
Name: oslili
Version: 0.15
Summary: Open Source License Identification Library
Home-page: https://github.com/oscarvalenzuelab/oslili
Author: Oscar Valenzuela B.
Author-email: alkamod@gmail.com
License: Apache-2.0
Classifier: Programming Language :: Python :: 3
Classifier: Operating System :: POSIX :: Linux
Classifier: Development Status :: 3 - Alpha
Classifier: License :: OSI Approved :: Apache Software License
License-File: LICENSE
License-File: NOTICE
Requires-Dist: scikit-learn ==1.4.2
Requires-Dist: ssdeep
